pylinebot/__init__.py
pylinebot/client.py
pylinebot-2.0.dist-info/LICENSE
pylinebot-2.0.dist-info/METADATA
pylinebot-2.0.dist-info/WHEEL
pylinebot-2.0.dist-info/top_level.txt
pylinebot-2.0.dist-info/RECORD
